nautobot/__init__.py
nautobot/apps/__init__.py
nautobot/apps/admin.py
nautobot/apps/api.py
nautobot/apps/change_logging.py
nautobot/apps/choices.py
nautobot/apps/config.py
nautobot/apps/constants.py
nautobot/apps/datasources.py
nautobot/apps/events.py
nautobot/apps/exceptions.py
nautobot/apps/factory.py
nautobot/apps/filters.py
nautobot/apps/forms.py
nautobot/apps/graphql.py
nautobot/apps/jobs.py
nautobot/apps/models.py
nautobot/apps/querysets.py
nautobot/apps/secrets.py
nautobot/apps/tables.py
nautobot/apps/templatetags.py
nautobot/apps/testing.py
nautobot/apps/ui.py
nautobot/apps/urls.py
nautobot/apps/utils.py
nautobot/apps/views.py
nautobot/circuits/__init__.py
nautobot/circuits/api/__init__.py
nautobot/circuits/api/serializers.py
nautobot/circuits/api/urls.py
nautobot/circuits/api/views.py
nautobot/circuits/apps.py
nautobot/circuits/choices.py
nautobot/circuits/factory.py
nautobot/circuits/filters.py
nautobot/circuits/forms.py
nautobot/circuits/graphql/__init__.py
nautobot/circuits/graphql/types.py
nautobot/circuits/homepage.py
nautobot/circuits/migrations/0001_initial_part_1.py
nautobot/circuits/migrations/0002_initial_part_2.py
nautobot/circuits/migrations/0003_auto_slug.py
nautobot/circuits/migrations/0004_increase_provider_account_length.py
nautobot/circuits/migrations/0005_providernetwork.py
nautobot/circuits/migrations/0006_cache_circuit_terminations.py
nautobot/circuits/migrations/0007_circuitterminations_primary_model.py
nautobot/circuits/migrations/0008_add_natural_indexing.py
nautobot/circuits/migrations/0009_circuittermination_location.py
nautobot/circuits/migrations/0010_rename_foreign_keys_and_related_names.py
nautobot/circuits/migrations/0011_remove_site_foreign_key_from_circuit_termination_class.py
nautobot/circuits/migrations/0012_created_datetime.py
nautobot/circuits/migrations/0013_alter_circuittermination__path.py
nautobot/circuits/migrations/0014_related_name_changes.py
nautobot/circuits/migrations/0015_remove_circuittype_provider_slug.py
nautobot-3.0.2.dist-info/LICENSE.txt
nautobot-3.0.2.dist-info/METADATA
nautobot-3.0.2.dist-info/NOTICE
nautobot-3.0.2.dist-info/WHEEL
nautobot-3.0.2.dist-info/entry_points.txt
nautobot-3.0.2.dist-info/RECORD
