Metadata-Version: 2.3
Name: nautobot
Version: 3.0.2
Summary: Source of truth and network automation platform.
License: Apache-2.0
Keywords: Nautobot
Author: Network to Code
Author-email: opensource@networktocode.com
Requires-Python: >=3.10,<3.14
Classifier: Development Status :: 5 - Production/Stable
Classifier: Intended Audience :: Developers
Classifier: License :: OSI Approved :: Apache Software License
Classifier: Programming Language :: Python :: 3
Classifier: Programming Language :: Python :: 3.10
Classifier: Programming Language :: Python :: 3.11
Classifier: Programming Language :: Python :: 3.12
Classifier: Programming Language :: Python :: 3.13
Provides-Extra: all
Provides-Extra: ldap
Provides-Extra: mysql
Provides-Extra: napalm
Provides-Extra: remote-storage
Provides-Extra: sso
Requires-Dist: Django (>=4.2.27,<4.3.0)
Requires-Dist: GitPython (>=3.1.45,<3.2.0)
Requires-Dist: Jinja2 (>=3.1.6,<3.2.0)
Requires-Dist: Markdown (>=3.8.2,<3.9.0)
Requires-Dist: Pillow (>=12.0.0,<12.1.0)
Requires-Dist: PyYAML (>=6.0.3,<6.1.0)
Requires-Dist: celery (>=5.6.0,<5.7.0)
Requires-Dist: cryptography (>=46.0.3,<46.1.0)
Requires-Dist: django-ajax-tables (>=1.1.1,<1.2.0)
Requires-Dist: django-auth-ldap (>=5.2.0,<5.3.0) ; extra == "all" or extra == "ldap"
Requires-Dist: django-celery-beat (>=2.7.0,<2.8.0)
Requires-Dist: django-celery-results (>=2.6.0,<2.7.0)
Requires-Dist: django-constance (>=4.3.4,<4.4.0)
Requires-Dist: django-cors-headers (>=4.9.0,<4.10.0)
Requires-Dist: django-db-file-storage (>=0.5.6.1,<0.6.0.0)
Requires-Dist: django-extensions (>=4.1,<4.2)
Requires-Dist: django-filter (>=25.1,<25.2)
Requires-Dist: django-health-check (>=3.20.0,<3.21.0)
Requires-Dist: django-jinja (>=2.11.0,<2.12.0)
Requires-Dist: django-prometheus (>=2.4.1,<2.5.0)
Requires-Dist: django-redis (>=6.0.0,<6.1.0)
Requires-Dist: django-silk (>=5.4.3,<5.5.0)
Requires-Dist: django-storages (>=1.14.6,<1.15.0) ; extra == "all" or extra == "remote-storage"
Requires-Dist: django-structlog[celery] (>=10.0.0,<10.1.0)
Requires-Dist: django-tables2 (>=2.8.0,<2.9.0)
Requires-Dist: django-taggit (>=6.1.0,<6.2.0)
Requires-Dist: django-timezone-field (>=7.2.1,<7.3.0)
Requires-Dist: django-tree-queries (>=0.23.0,<0.24.0)
Requires-Dist: django-webserver (>=1.2.0,<1.3.0)
Requires-Dist: djangorestframework (>=3.16.1,<3.17.0)
Requires-Dist: drf-spectacular[sidecar] (>=0.28.0,<0.29.0)
Requires-Dist: emoji (>=2.15.0,<2.16.0)
Requires-Dist: graphene-django (>=3.2.3,<3.3.0)
Requires-Dist: graphene-django-optimizer (>=0.10.0,<0.11.0)
Requires-Dist: jsonschema (>=4.7.0,<5.0.0)
Requires-Dist: kubernetes (>=33.1.0,<34.0.0)
Requires-Dist: mysqlclient (>=2.2.7,<2.3.0) ; extra == "all" or extra == "mysql"
Requires-Dist: napalm (>=4.1.0,<6.0.0) ; extra == "all" or extra == "napalm"
Requires-Dist: netaddr (>=1.3.0,<1.4.0)
Requires-Dist: netutils (>=1.14.0,<2.0.0)
Requires-Dist: nh3 (>=0.3.2,<0.4.0)
Requires-Dist: packaging (>=23.1)
Requires-Dist: prometheus-client (>=0.23.1,<0.24.0)
Requires-Dist: psycopg2-binary (>=2.9.11,<2.10.0)
Requires-Dist: python-slugify (>=8.0.4,<8.1.0)
Requires-Dist: pyuwsgi (>=2.0.30,<2.1.0)
Requires-Dist: social-auth-app-django (>=5.4.3,<5.5.0)
Requires-Dist: social-auth-core[saml] (>=4.8.1,<4.9.0) ; extra == "all" or extra == "sso"
Requires-Dist: svgwrite (>=1.4.3,<1.5.0)
Project-URL: Documentation, https://docs.nautobot.com
Project-URL: Homepage, https://nautobot.com
Project-URL: Repository, https://github.com/nautobot/nautobot
